[{"name":"render_template.action_view","payload":{"identifier":"/Users/Scotty/Documents/WDIWork/WDI_LDN_5_Assignments/ScottyGammon/7Week/1Dw7/wdi-w7d1-haml_and_sass/app/views/home/haml_practice.html.haml","layout":"layouts/application","exception":["ActionView::Template::Error","The line was indented 2 levels deeper than the previous line."]},"time":"2014-05-12T12:00:07+01:00","transaction_id":"1120d56a19c9cc3338ce","end":"2014-05-12T12:00:07+01:00","duration":2.029},{"name":"process_action.action_controller","payload":{"controller":"HomeController","action":"haml_practice","params":{"controller":"home","action":"haml_practice"},"format":"html","method":"GET","path":"/practice","exception":["ActionView::Template::Error","The line was indented 2 levels deeper than the previous line."],"status":"500"},"time":"2014-05-12T12:00:07+01:00","transaction_id":"1120d56a19c9cc3338ce","end":"2014-05-12T12:00:07+01:00","duration":7.853000000000001},{"name":"process_action.action_controller.exception","payload":{"call":"ActionView::Template::Error (The line was indented 2 levels deeper than the previous line.)"},"time":0,"transaction_id":null,"end":0,"duration":0.0},{"name":"process_action.action_controller.exception","payload":{"call":"app/views/home/haml_practice.html.haml:5"},"time":0,"transaction_id":null,"end":0,"duration":0.0}]